mindocr/__init__.py
mindocr/version.py
mindocr/data/README.md
mindocr/data/README_CN.md
mindocr/data/__init__.py
mindocr/data/base_dataset.py
mindocr/data/builder.py
mindocr/data/constants.py
mindocr/data/det_dataset.py
mindocr/data/kie_dataset.py
mindocr/data/layout_dataset.py
mindocr/data/pgnet_dataset.py
mindocr/data/predict_dataset.py
mindocr/data/rec_dataset.py
mindocr/data/rec_lmdb_dataset.py
mindocr/data/table_pubtab_dataset.py
mindocr/data/transforms/README.md
mindocr/data/transforms/README_CN.md
mindocr/data/transforms/__init__.py
mindocr/data/transforms/det_east_transforms.py
mindocr/data/transforms/det_fce_transforms.py
mindocr/data/transforms/det_transforms.py
mindocr/data/transforms/e2e_transforms.py
mindocr/data/transforms/general_transforms.py
mindocr/data/transforms/layoutlm_transforms.py
mindocr/data/transforms/llm_transform.py
mindocr/data/transforms/pgnet_transforms.py
mindocr/data/transforms/rec_abinet_transforms.py
mindocr/data/transforms/rec_transforms.py
mindocr/data/transforms/svtr_transform.py
mindocr/data/transforms/table_transform.py
mindocr/data/transforms/transforms_factory.py
mindocr/data/utils/collate_fn.py
mindocr/data/utils/polygon_utils.py
mindocr/engine/README.md
mindocr/engine/README_CN.md
mindocr/engine/__init__.py
mindocr/engine/detmodel.py
mindocr/engine/modelengine.py
mindocr/engine/postprocessor.py
mindocr/engine/preprocessor.py
mindocr/engine/recmodel.py
mindocr/engine/utils.py
mindocr/engine/default_cfg/postprocess.yaml
mindocr/engine/default_cfg/preprocess.yaml
mindocr/losses/__init__.py
mindocr/losses/abinet_loss.py
mindocr/losses/builder.py
mindocr/losses/cls_loss.py
mindocr/losses/det_loss.py
mindocr/losses/kie_loss.py
mindocr/losses/pg_loss.py
mindocr/losses/rec_loss.py
mindocr/losses/rec_multi_loss.py
mindocr/losses/table_master_loss.py
mindocr/losses/yolov8_loss.py
mindocr/metrics/__init__.py
mindocr/metrics/builder.py
mindocr/metrics/cls_metrics.py
mindocr/metrics/det_metrics.py
mindocr/metrics/e2e_metrics.py
opensourcedot_mindocr-0.5.1.dist-info/LICENSE
opensourcedot_mindocr-0.5.1.dist-info/METADATA
opensourcedot_mindocr-0.5.1.dist-info/WHEEL
opensourcedot_mindocr-0.5.1.dist-info/top_level.txt
opensourcedot_mindocr-0.5.1.dist-info/RECORD
